jsonschema_cn/__init__.py
jsonschema_cn/__main__.py
jsonschema_cn/cli.py
jsonschema_cn/grammar.py
jsonschema_cn/parse.py
jsonschema_cn/test.py
jsonschema_cn/tree.py
jsonschema_cn/unspace.py
jsonschema_cn/visitor.py
jsonschema_cn-0.15.dist-info/METADATA
jsonschema_cn-0.15.dist-info/WHEEL
jsonschema_cn-0.15.dist-info/entry_points.txt
jsonschema_cn-0.15.dist-info/top_level.txt
jsonschema_cn-0.15.dist-info/RECORD
