Metadata-Version: 2.1
Name: jsonschema-cn
Version: 0.15
Summary: Compact notation for JSON Schemas
Home-page: http://github.com/fab13n/jsonschema_cn
Author: Fabien Fleutot
Author-email: fleutot@gmail.com
License: BSD
Keywords: DSL JSON schema jsonschema
Platform: UNKNOWN
Classifier: Development Status :: 3 - Alpha
Classifier: License :: OSI Approved :: BSD License
Classifier: Programming Language :: Python :: 3.6
Classifier: Operating System :: OS Independent
Requires-Dist: jsonschema (>=3.0.1)
Requires-Dist: parsimonious (>=0.8.0)
